pyrainer/__init__.py
pyrainer/cli.py
pyrainer/commit.py
pyrainer/http.py
pyrainer/rainer.py
pyrainer/util.py
pyrainer-0.26.dist-info/licenses/LICENSE
pyrainer-0.26.dist-info/METADATA
pyrainer-0.26.dist-info/WHEEL
pyrainer-0.26.dist-info/top_level.txt
pyrainer-0.26.dist-info/RECORD
