Metadata-Version: 2.4
Name: pyrainer
Version: 0.26
Summary: Python client for Rainer
Author-email: gian <gianmerlino@gmail.com>
Project-URL: Homepage, https://github.com/metamx/rainer
Requires-Python: >=3.7
License-File: LICENSE
Requires-Dist: termcolor>=2.3.0
Requires-Dist: PyYaml>=6.0
Dynamic: license-file
